ngsildclient/__init__.py
ngsildclient/api/__init__.py
ngsildclient/api/alt.py
ngsildclient/api/asyn/__init__.py
ngsildclient/api/asyn/batch.py
ngsildclient/api/asyn/client.py
ngsildclient/api/asyn/contexts.py
ngsildclient/api/asyn/entities.py
ngsildclient/api/asyn/subscriptions.py
ngsildclient/api/asyn/temporal.py
ngsildclient/api/asyn/types.py
ngsildclient/api/batch.py
ngsildclient/api/client.py
ngsildclient/api/constants.py
ngsildclient/api/contexts.py
ngsildclient/api/entities.py
ngsildclient/api/exceptions.py
ngsildclient/api/follow.py
ngsildclient/api/helper/__init__.py
ngsildclient/api/helper/subscription.py
ngsildclient/api/helper/temporal.py
ngsildclient/api/subscriptions.py
ngsildclient/api/temporal.py
ngsildclient/api/temporal_alt.py
ngsildclient/api/types.py
ngsildclient/exceptions.py
ngsildclient/model/__init__.py
ngsildclient/model/attr/__init__.py
ngsildclient/model/attr/factory.py
ngsildclient/model/attr/geo.py
ngsildclient/model/attr/prop.py
ngsildclient/model/attr/rel.py
ngsildclient/model/attr/temporal.py
ngsildclient/model/constants.py
ngsildclient/model/entity.py
ngsildclient/model/exceptions.py
ngsildclient/model/helper/__init__.py
ngsildclient/model/helper/openinghours.py
ngsildclient/model/helper/postal.py
ngsildclient/model/ngsidict.py
ngsildclient/model/utils.py
ngsildclient/settings.py
ngsildclient/utils/__init__.py
ngsildclient/utils/console.py
ngsildclient/utils/dataviz.py
ngsildclient/utils/iso8601.py
ngsildclient/utils/sentinel.py
ngsildclient/utils/url.py
ngsildclient/utils/urn.py
ngsildclient/utils/uuid.py
ngsildclient-0.5.1.dist-info/LICENSE.txt
ngsildclient-0.5.1.dist-info/WHEEL
ngsildclient-0.5.1.dist-info/METADATA
ngsildclient-0.5.1.dist-info/RECORD
