Metadata-Version: 2.1
Name: ngsildclient
Version: 0.5.1
Summary: A Python library that helps building NGSI-LD entities and interacting with a NGSI-LD Context Broker
Home-page: https://github.com/Orange-OpenSource/python-ngsild-client
License: Apache-2.0
Keywords: Fiware,NGSI,NGSI-LD,NGSI Agent
Author: fbattello
Author-email: fabien.battello@orange.com
Requires-Python: >=3.9,<4.0
Classifier: License :: OSI Approved :: Apache Software License
Classifier: Programming Language :: Python :: 3
Classifier: Programming Language :: Python :: 3.10
Classifier: Programming Language :: Python :: 3.9
Classifier: Topic :: Software Development :: Libraries :: Python Modules
Requires-Dist: aiofiles (>=0.8.0,<0.9.0)
Requires-Dist: geojson (>=2.5.0,<3.0.0)
Requires-Dist: httpx (>=0.23.0,<0.24.0)
Requires-Dist: isodate (>=0.6.1,<0.7.0)
Requires-Dist: multipledispatch (>=0.6.0,<0.7.0)
Requires-Dist: networkx (>=2.8.7,<3.0.0)
Requires-Dist: python-dateutil (>=2.8.2,<3.0.0)
Requires-Dist: requests (>=2.26.0,<3.0.0)
Requires-Dist: rich (>=12.4.1,<13.0.0)
Requires-Dist: scalpl (>=0.4.2,<0.5.0)
